pugnlp/__init__.py
pugnlp/charlist.py
pugnlp/constants.py
pugnlp/data.py
pugnlp/detector_morse.py
pugnlp/futil.py
pugnlp/penn_treebank_tokenizer.py
pugnlp/plots.py
pugnlp/regexes.py
pugnlp/segmentation.py
pugnlp/sentence_segmentation.py
pugnlp/stats.py
pugnlp/tutil.py
pugnlp/util.py
pugnlp/data/ascii-equivalents.csv
pugnlp/data/ascii-equivalents.ods
pugnlp/data/emojione-activities.txt
pugnlp/data/emojione-animals-and-nature.txt
pugnlp/data/emojione-flags.txt
pugnlp/data/emojione-food-and-drink.txt
pugnlp/data/emojione-objects.txt
pugnlp/data/emojione-smilies.txt
pugnlp/data/emojione-symbols.txt
pugnlp/data/emojione-travel-and-places.txt
pugnlp/data/emoticons-from-wikipedia.csv
pugnlp/data/emoticons-from-wikipedia.ods
pugnlp/data/goodreads-omniscient-books.txt
pugnlp/data/tlds-from-iana.csv
pugnlp/data/uri-schemes.csv
pugnlp/data/uri-schemes.xhtml.csv
pugnlp/data/wsj_pugnlp.detector_morse.Detector.json.gz
pugnlp/scripts/__init__.py
pugnlp/scripts/bon_lsi.py
pugnlp/scripts/delint_working_dir
pugnlp/scripts/pre-commit
pugnlp-0.2.6.dist-info/AUTHORS.rst
pugnlp-0.2.6.dist-info/LICENSE.txt
pugnlp-0.2.6.dist-info/METADATA
pugnlp-0.2.6.dist-info/WHEEL
pugnlp-0.2.6.dist-info/entry_points.txt
pugnlp-0.2.6.dist-info/top_level.txt
pugnlp-0.2.6.dist-info/RECORD
