Metadata-Version: 2.1
Name: pugnlp
Version: 0.2.6
Summary: Python Natural Language Processing by and for the Python User Group in Portland, OR
Home-page: http://github.com/totalgood/pugnlp/
Author: Hobson Lane et al
Author-email: github@totalgood.com
License: mit
Platform: any
Classifier: Development Status :: 4 - Beta
Classifier: Programming Language :: Python
Classifier: Programming Language :: Python :: 2.7
Classifier: Programming Language :: Python :: 3.5
Classifier: Environment :: Console
Classifier: Intended Audience :: Developers
Classifier: License :: OSI Approved :: MIT License
Classifier: Operating System :: OS Independent
Classifier: Topic :: Software Development :: Libraries :: Python Modules
Classifier: Topic :: Text Processing :: Linguistic
Classifier: Topic :: Text Processing :: Filters
Classifier: Topic :: Text Processing :: General
Classifier: Topic :: Text Processing :: Indexing
Classifier: Topic :: Scientific/Engineering :: Mathematics
Classifier: Topic :: Scientific/Engineering :: Artificial Intelligence
Requires-Dist: coverage
Requires-Dist: future
Requires-Dist: fuzzywuzzy
Requires-Dist: jupyter
Requires-Dist: matplotlib
Requires-Dist: nltk
Requires-Dist: pandas
Requires-Dist: pip
Requires-Dist: pypandoc
Requires-Dist: python-Levenshtein
Requires-Dist: python-slugify
Requires-Dist: scikit-learn
Requires-Dist: scipy
Requires-Dist: plotly
Requires-Dist: seaborn
Requires-Dist: tqdm
Requires-Dist: wheel
Requires-Dist: gensim
